{
	"db":
	{
		"host": "localhost",
		"user": "root",
		"password": "pass",
		"database": "queue" 
	},
	"server":
	{
		"whiteListIpAdresses": ["::1", "127.0.0.1", "8.8.8.8"],
		"httpPort": 8080, 
		"httpsPort": 8081,
		"ssl":
		{
			"active": false, 
			"keyFile": "ssl/key.pem",
			"certFile": "ssl/cert.pem"
		}
	},
	"consumer":
	{
		"sleepForSeconds": 1
	},
	"email":
	{
		"active": false,
		"setting":
		{
			"user": "username",
			"password": "123456",
			"host": "domain.com",
			"port": 587,
			"ssl": false,
			"tls":
			{
				"rejectUnauthorized": false
			}
		},
		"sender": "mail@domain.com"
	}

}
